lightweight_ratelimit_django/__init__.py
lightweight_ratelimit_django/rate_limiter/__init__.py
lightweight_ratelimit_django/rate_limiter/limiter.py
lightweight_ratelimit_django/rate_limiter/runtests.py
lightweight_ratelimit_django/rate_limiter/settings.py
lightweight_ratelimit_django/rate_limiter/tests/__init__.py
lightweight_ratelimit_django/rate_limiter/tests/test_limiter.py
lightweight_ratelimit_django/rate_limiter/utils/__init__.py
lightweight_ratelimit_django/rate_limiter/utils/utils.py
lightweight_ratelimit_django/rate_limiter/utils/tests/__init__.py
lightweight_ratelimit_django/rate_limiter/utils/tests/test_utils.py
lightweight_ratelimit_django-1.0.7.dist-info/licenses/LICENSE
lightweight_ratelimit_django-1.0.7.dist-info/METADATA
lightweight_ratelimit_django-1.0.7.dist-info/WHEEL
lightweight_ratelimit_django-1.0.7.dist-info/top_level.txt
lightweight_ratelimit_django-1.0.7.dist-info/RECORD
