Metadata-Version: 2.4
Name: lightweight-ratelimit-django
Version: 1.0.7
Summary: Lightweight, decorator-based rate limiting for Django views using TTL-based cache keys.
Author-email: Vazgen Ayvazyan <a.wasgen@gmail.com>
License: MIT
Project-URL: Homepage, https://github.com/VazgenAyv/lightweight_ratelimit_django
Project-URL: Repository, https://github.com/VazgenAyv/lightweight_ratelimit_django.git
Requires-Python: >=3.11
License-File: LICENSE
Requires-Dist: Django>=4.2
Dynamic: license-file
